snakemake_logger_plugin_rich/__init__.py
snakemake_logger_plugin_rich/event_handler.py
snakemake_logger_plugin_rich/events.py
snakemake_logger_plugin_rich/handler.py
snakemake_logger_plugin_rich-0.4.0.dist-info/METADATA
snakemake_logger_plugin_rich-0.4.0.dist-info/WHEEL
snakemake_logger_plugin_rich-0.4.0.dist-info/RECORD
